{
  "Name": "airflow-serverless",
  "Actions": [
    {
      "Name": "CreateWorkflow",
      "ActionConditionKeys": [
        "aws:RequestTag/${TagKey}",
        "aws:TagKeys"
      ],
      "Annotations": {
        "Properties": {
          "IsList": false,
          "IsPermissionManagement": false,
          "IsTaggingOnly": false,
          "IsWrite": true
        }
      },
      "SupportedBy": {
        "IAM Access Analyzer Policy Generation": false,
        "IAM Action Last Accessed": false
      }
    },
    {
      "Name": "DeleteWorkflow",
      "Annotations": {
        "Properties": {
          "IsList": false,
          "IsPermissionManagement": false,
          "IsTaggingOnly": false,
          "IsWrite": true
        }
      },
      "Resources": [
        {
          "Name": "Workflow"
        }
      ],
      "SupportedBy": {
        "IAM Access Analyzer Policy Generation": false,
        "IAM Action Last Accessed": false
      }
    },
    {
      "Name": "GetTaskInstance",
      "Annotations": {
        "Properties": {
          "IsList": false,
          "IsPermissionManagement": false,
          "IsTaggingOnly": false,
          "IsWrite": false
        }
      },
      "Resources": [
        {
          "Name": "Workflow"
        }
      ],
      "SupportedBy": {
        "IAM Access Analyzer Policy Generation": false,
        "IAM Action Last Accessed": false
      }
    },
    {
      "Name": "GetWorkflow",
      "Annotations": {
        "Properties": {
          "IsList": false,
          "IsPermissionManagement": false,
          "IsTaggingOnly": false,
          "IsWrite": false
        }
      },
      "Resources": [
        {
          "Name": "Workflow"
        }
      ],
      "SupportedBy": {
        "IAM Access Analyzer Policy Generation": false,
        "IAM Action Last Accessed": false
      }
    },
    {
      "Name": "GetWorkflowRun",
      "Annotations": {
        "Properties": {
          "IsList": false,
          "IsPermissionManagement": false,
          "IsTaggingOnly": false,
          "IsWrite": false
        }
      },
      "Resources": [
        {
          "Name": "Workflow"
        }
      ],
      "SupportedBy": {
        "IAM Access Analyzer Policy Generation": false,
        "IAM Action Last Accessed": false
      }
    },
    {
      "Name": "ListTagsForResource",
      "ActionConditionKeys": [
        "aws:ResourceTag/${TagKey}"
      ],
      "Annotations": {
        "Properties": {
          "IsList": false,
          "IsPermissionManagement": false,
          "IsTaggingOnly": false,
          "IsWrite": false
        }
      },
      "Resources": [
        {
          "Name": "Workflow"
        }
      ],
      "SupportedBy": {
        "IAM Access Analyzer Policy Generation": false,
        "IAM Action Last Accessed": false
      }
    },
    {
      "Name": "ListTaskInstances",
      "Annotations": {
        "Properties": {
          "IsList": true,
          "IsPermissionManagement": false,
          "IsTaggingOnly": false,
          "IsWrite": false
        }
      },
      "Resources": [
        {
          "Name": "Workflow"
        }
      ],
      "SupportedBy": {
        "IAM Access Analyzer Policy Generation": false,
        "IAM Action Last Accessed": false
      }
    },
    {
      "Name": "ListWorkflowRuns",
      "Annotations": {
        "Properties": {
          "IsList": true,
          "IsPermissionManagement": false,
          "IsTaggingOnly": false,
          "IsWrite": false
        }
      },
      "Resources": [
        {
          "Name": "Workflow"
        }
      ],
      "SupportedBy": {
        "IAM Access Analyzer Policy Generation": false,
        "IAM Action Last Accessed": false
      }
    },
    {
      "Name": "ListWorkflowVersions",
      "Annotations": {
        "Properties": {
          "IsList": true,
          "IsPermissionManagement": false,
          "IsTaggingOnly": false,
          "IsWrite": false
        }
      },
      "Resources": [
        {
          "Name": "Workflow"
        }
      ],
      "SupportedBy": {
        "IAM Access Analyzer Policy Generation": false,
        "IAM Action Last Accessed": false
      }
    },
    {
      "Name": "ListWorkflows",
      "Annotations": {
        "Properties": {
          "IsList": true,
          "IsPermissionManagement": false,
          "IsTaggingOnly": false,
          "IsWrite": false
        }
      },
      "SupportedBy": {
        "IAM Access Analyzer Policy Generation": false,
        "IAM Action Last Accessed": false
      }
    },
    {
      "Name": "StartWorkflowRun",
      "Annotations": {
        "Properties": {
          "IsList": false,
          "IsPermissionManagement": false,
          "IsTaggingOnly": false,
          "IsWrite": true
        }
      },
      "Resources": [
        {
          "Name": "Workflow"
        }
      ],
      "SupportedBy": {
        "IAM Access Analyzer Policy Generation": false,
        "IAM Action Last Accessed": false
      }
    },
    {
      "Name": "StopWorkflowRun",
      "Annotations": {
        "Properties": {
          "IsList": false,
          "IsPermissionManagement": false,
          "IsTaggingOnly": false,
          "IsWrite": true
        }
      },
      "Resources": [
        {
          "Name": "Workflow"
        }
      ],
      "SupportedBy": {
        "IAM Access Analyzer Policy Generation": false,
        "IAM Action Last Accessed": false
      }
    },
    {
      "Name": "TagResource",
      "ActionConditionKeys": [
        "aws:RequestTag/${TagKey}",
        "aws:ResourceTag/${TagKey}",
        "aws:TagKeys"
      ],
      "Annotations": {
        "Properties": {
          "IsList": false,
          "IsPermissionManagement": false,
          "IsTaggingOnly": true,
          "IsWrite": true
        }
      },
      "Resources": [
        {
          "Name": "Workflow"
        }
      ],
      "SupportedBy": {
        "IAM Access Analyzer Policy Generation": false,
        "IAM Action Last Accessed": false
      }
    },
    {
      "Name": "UntagResource",
      "ActionConditionKeys": [
        "aws:ResourceTag/${TagKey}",
        "aws:TagKeys"
      ],
      "Annotations": {
        "Properties": {
          "IsList": false,
          "IsPermissionManagement": false,
          "IsTaggingOnly": true,
          "IsWrite": true
        }
      },
      "Resources": [
        {
          "Name": "Workflow"
        }
      ],
      "SupportedBy": {
        "IAM Access Analyzer Policy Generation": false,
        "IAM Action Last Accessed": false
      }
    },
    {
      "Name": "UpdateWorkflow",
      "Annotations": {
        "Properties": {
          "IsList": false,
          "IsPermissionManagement": false,
          "IsTaggingOnly": false,
          "IsWrite": true
        }
      },
      "Resources": [
        {
          "Name": "Workflow"
        }
      ],
      "SupportedBy": {
        "IAM Access Analyzer Policy Generation": false,
        "IAM Action Last Accessed": false
      }
    }
  ],
  "ConditionKeys": [
    {
      "Name": "aws:RequestTag/${TagKey}",
      "Types": [
        "String"
      ]
    },
    {
      "Name": "aws:ResourceTag/${TagKey}",
      "Types": [
        "String"
      ]
    },
    {
      "Name": "aws:TagKeys",
      "Types": [
        "ArrayOfString"
      ]
    }
  ],
  "Resources": [
    {
      "Name": "Workflow",
      "ARNFormats": [
        "arn:${Partition}:airflow-serverless:${Region}:${Account}:workflow/${WorkflowId}"
      ],
      "ConditionKeys": [
        "aws:ResourceTag/${TagKey}"
      ]
    }
  ],
  "Version": "v1.4"
}